xyShiftSplit/__init__.py
xyShiftSplit/xyShiftSplit.py
xyShiftSplit-0.0.6.dist-info/LICENSE
xyShiftSplit-0.0.6.dist-info/METADATA
xyShiftSplit-0.0.6.dist-info/WHEEL
xyShiftSplit-0.0.6.dist-info/top_level.txt
xyShiftSplit-0.0.6.dist-info/RECORD
