Metadata-Version: 2.1
Name: xyShiftSplit
Version: 0.0.6
Summary: this package to make easy to create X and Y data, shift and split from same dataset
Home-page: UNKNOWN
Author: Rifqi khairurrahman
Author-email: eaglemaster7@gmail.com
License: UNKNOWN
Platform: UNKNOWN
Classifier: Programming Language :: Python :: 3
Classifier: License :: OSI Approved :: MIT License
Classifier: Operating System :: OS Independent
Requires-Python: >=3.6
License-File: LICENSE
